kingbird_dashboard/__init__.py
kingbird_dashboard/karma.conf.js
kingbird_dashboard/version.py
kingbird_dashboard/api/__init__.py
kingbird_dashboard/api/client.py
kingbird_dashboard/api/rest_api.py
kingbird_dashboard/content/__init__.py
kingbird_dashboard/content/kingbirds/__init__.py
kingbird_dashboard/content/kingbirds/panel.py
kingbird_dashboard/content/kingbirds/tests.py
kingbird_dashboard/content/kingbirds/urls.py
kingbird_dashboard/enabled/_90_kingbird_kingbird_panelgroup.py
kingbird_dashboard/enabled/_91_kingbird_kingbird_kingbirds_panel.py
kingbird_dashboard/enabled/__init__.py
kingbird_dashboard/static/dashboard/kingbird/kingbird.module.js
kingbird_dashboard/static/dashboard/kingbird/kingbird.module.spec.js
kingbird_dashboard/static/dashboard/kingbird/kingbird.scss
kingbird_dashboard/static/dashboard/kingbird/kingbird_dashboard.service.js
kingbird_dashboard/static/dashboard/kingbird/kingbirds/kingbirds.module.js
kingbird_dashboard/static/dashboard/kingbird/kingbirds/kingbirds.module.spec.js
kingbird_dashboard/static/dashboard/kingbird/kingbirds/kingbirds.scss
kingbird_dashboard/static/dashboard/kingbird/kingbirds/kingbirds.service.js
kingbird_dashboard/static/dashboard/kingbird/kingbirds/kingbirds.service.spec.js
kingbird_dashboard/static/dashboard/kingbird/kingbirds/panel.html
kingbird_dashboard/static/dashboard/kingbird/kingbirds/actions/actions.module.js
kingbird_dashboard/static/dashboard/kingbird/kingbirds/actions/create.service.js
kingbird_dashboard/static/dashboard/kingbird/kingbirds/actions/delete.service.js
kingbird_dashboard/static/dashboard/kingbird/kingbirds/actions/update.service.js
kingbird_dashboard/static/dashboard/kingbird/kingbirds/details/details.module.js
kingbird_dashboard/static/dashboard/kingbird/kingbirds/details/drawer.html
kingbird_dashboard/static/dashboard/kingbird/kingbirds/details/overview.controller.js
kingbird_dashboard/static/dashboard/kingbird/kingbirds/details/overview.html
kingbird_dashboard-0.0.0.dist-info/DESCRIPTION.rst
kingbird_dashboard-0.0.0.dist-info/METADATA
kingbird_dashboard-0.0.0.dist-info/RECORD
kingbird_dashboard-0.0.0.dist-info/WHEEL
kingbird_dashboard-0.0.0.dist-info/metadata.json
kingbird_dashboard-0.0.0.dist-info/pbr.json
kingbird_dashboard-0.0.0.dist-info/top_level.txt
