Metadata-Version: 2.0
Name: kingbird-dashboard
Version: 0.0.0
Summary: User Interface for Kingbird
Home-page: http://www.openstack.org/
Author: OpenStack
Author-email: openstack-dev@lists.openstack.org
License: UNKNOWN
Platform: UNKNOWN
Classifier: Environment :: OpenStack
Classifier: Intended Audience :: Information Technology
Classifier: Intended Audience :: System Administrators
Classifier: License :: OSI Approved :: Apache Software License
Classifier: Operating System :: POSIX :: Linux
Classifier: Programming Language :: Python
Classifier: Programming Language :: Python :: 2
Classifier: Programming Language :: Python :: 2.7
Classifier: Programming Language :: Python :: 3
Classifier: Programming Language :: Python :: 3.5
Requires-Dist: Django (>=1.8,<2.0)
Requires-Dist: PyYAML (>=3.10)
Requires-Dist: django-compressor (>=2.0)
Requires-Dist: iso8601 (>=0.1.11)
Requires-Dist: pbr (!=2.1.0,>=2.0.0)
